cloudops/__init__.py
cloudops/logging/__init__.py
cloudops/logging/google/__init__.py
cloudops/logging/google/logging.py
cloudops_logging_google-0.1.7.dist-info/LICENSE
cloudops_logging_google-0.1.7.dist-info/METADATA
cloudops_logging_google-0.1.7.dist-info/WHEEL
cloudops_logging_google-0.1.7.dist-info/RECORD
