Metadata-Version: 2.1
Name: cloudops-logging-google
Version: 0.1.7
Summary: 
Home-page: https://github.com/manucalop/cloudops-logging-google
License: MIT
Author: Manuel Castillo-Lopez
Author-email: manucalop@gmail.com
Requires-Python: >=3.9,<4.0
Classifier: License :: OSI Approved :: MIT License
Classifier: Programming Language :: Python :: 3
Classifier: Programming Language :: Python :: 3.9
Classifier: Programming Language :: Python :: 3.10
Classifier: Programming Language :: Python :: 3.11
Classifier: Programming Language :: Python :: 3.12
Provides-Extra: colors
Requires-Dist: colorlog (>=6.8.0,<7.0.0) ; extra == "colors"
Requires-Dist: google-cloud-logging (>=3.5.0,<4.0.0)
Requires-Dist: pyyaml (>=6.0,<7.0)
Project-URL: Repository, https://github.com/manucalop/cloudops-logging-google
